{
  "$id": "urn:designer:primitive:color-modifier-h-s-l",
  "type": "object",
  "properties": {
    "space": {
      "type": "string",
      "const": "hsl"
    },
    "h": {
      "$ref": "urn:designer:primitive:number-modifier"
    },
    "s": {
      "$ref": "urn:designer:primitive:number-modifier"
    },
    "l": {
      "$ref": "urn:designer:primitive:number-modifier"
    }
  },
  "additionalProperties": false,
  "required": [
    "space"
  ],
  "$schema": "http://json-schema.org/draft-07/schema#"
}